filmaffinity/__init__.py
filmaffinity/cli.py
filmaffinity/exporters.py
filmaffinity/py.typed
filmaffinity/scraper.py
filmaffinity_backup-1.2.1.dist-info/licenses/LICENSE
imdb_uploader/__init__.py
imdb_uploader/browser_automation.py
imdb_uploader/cli.py
imdb_uploader/config.py
imdb_uploader/constants.py
imdb_uploader/csv_validator.py
imdb_uploader/data_processing.py
imdb_uploader/prompts.py
imdb_uploader/py.typed
imdb_uploader/reporting.py
imdb_uploader/uploader.py
filmaffinity_backup-1.2.1.dist-info/METADATA
filmaffinity_backup-1.2.1.dist-info/WHEEL
filmaffinity_backup-1.2.1.dist-info/entry_points.txt
filmaffinity_backup-1.2.1.dist-info/top_level.txt
filmaffinity_backup-1.2.1.dist-info/RECORD
