Metadata-Version: 2.4
Name: filmaffinity-backup
Version: 1.2.1
Summary: Backup FilmAffinity data to CSV and upload ratings to IMDb
Author: Ignacio Heredia, Pelayo García
License: AGPL-3.0-or-later
Project-URL: Homepage, https://github.com/oyale/filmaffinity-backup
Project-URL: Repository, https://github.com/oyale/filmaffinity-backup
Project-URL: Issues, https://github.com/oyale/filmaffinity-backup/issues
Classifier: Development Status :: 4 - Beta
Classifier: Environment :: Console
Classifier: Intended Audience :: End Users/Desktop
Classifier: License :: OSI Approved :: GNU Affero General Public License v3 or later (AGPLv3+)
Classifier: Operating System :: OS Independent
Classifier: Programming Language :: Python :: 3
Classifier: Programming Language :: Python :: 3.9
Classifier: Programming Language :: Python :: 3.10
Classifier: Programming Language :: Python :: 3.11
Classifier: Programming Language :: Python :: 3.12
Classifier: Programming Language :: Python :: 3.13
Classifier: Topic :: Multimedia :: Video
Classifier: Topic :: Utilities
Requires-Python: >=3.9
License-File: LICENSE
Requires-Dist: beautifulsoup4>=4.9.0
Requires-Dist: pandas>=1.3.0
Requires-Dist: requests>=2.25.0
Requires-Dist: rich>=10.0.0
Requires-Dist: typer>=0.4.0
Provides-Extra: imdb
Requires-Dist: selenium>=4.0.0; extra == "imdb"
Requires-Dist: webdriver-manager>=3.5.0; extra == "imdb"
Requires-Dist: cinemagoer>=2022.12.27; extra == "imdb"
Provides-Extra: dev
Requires-Dist: pytest>=7.0.0; extra == "dev"
Requires-Dist: pytest-cov>=3.0.0; extra == "dev"
Requires-Dist: pre-commit>=3.5.0; extra == "dev"
Requires-Dist: ruff>=0.8.0; extra == "dev"
Requires-Dist: mypy>=1.13.0; extra == "dev"
Requires-Dist: types-requests>=2.31.0; extra == "dev"
Requires-Dist: types-beautifulsoup4>=4.12.0; extra == "dev"
Requires-Dist: bump-my-version>=0.16.0; extra == "dev"
Provides-Extra: all
Requires-Dist: filmaffinity-backup[dev,imdb]; extra == "all"
Dynamic: license-file
